LICENSE
MANIFEST.in
README.md
setup.cfg
setup.py
wagtail_commonmark.egg-info/PKG-INFO
wagtail_commonmark.egg-info/SOURCES.txt
wagtail_commonmark.egg-info/dependency_links.txt
wagtail_commonmark.egg-info/requires.txt
wagtail_commonmark.egg-info/top_level.txt
wagtailcommonmark/__init__.py
wagtailcommonmark/blocks.py
wagtailcommonmark/edit_handlers.py
wagtailcommonmark/fields.py
wagtailcommonmark/jinja2tags.py
wagtailcommonmark/utils.py
wagtailcommonmark/widgets.py
wagtailcommonmark/static/wagtailcommonmark/css/codemirror.css
wagtailcommonmark/static/wagtailcommonmark/css/codemirror.custom.css
wagtailcommonmark/static/wagtailcommonmark/js/codemirror.addon.edit.continuelist.js
wagtailcommonmark/static/wagtailcommonmark/js/codemirror.attach.js
wagtailcommonmark/static/wagtailcommonmark/js/codemirror.js
wagtailcommonmark/static/wagtailcommonmark/js/codemirror.mode.markdown.js
wagtailcommonmark/templatetags/__init__.py
wagtailcommonmark/templatetags/wagtailcommonmark.py