Metadata-Version: 2.1
Name: wagtail-commonmark
Version: 0.2.0
Summary: Commonmark support for Wagtail
Home-page: https://github.com/belak/wagtail-commonmark
Author: Kaleb Elwert
Author-email: belak@coded.io
License: MIT
Platform: UNKNOWN
Classifier: Development Status :: 5 - Production/Stable
Classifier: Environment :: Web Environment
Classifier: Framework :: Django
Classifier: Framework :: Wagtail
Classifier: Intended Audience :: Developers
Classifier: License :: OSI Approved :: MIT License
Classifier: Operating System :: OS Independent
Classifier: Programming Language :: Python :: 3
Classifier: Programming Language :: Python
